{
  "_comment": "goethe B1 lesen Teil 1 — richtig_falsch x6. Rellena los [campos], usa un SLUG único, omite passageId si no hay pasaje.",
  "passages": [
    {
      "id": "de-b1-p-lesen-t1-{SLUG}",
      "module": "lesen",
      "title": "[Titel / title]",
      "text": "[Lesetext — 150–220 Wörter , Niveau B1]",
      "passageVocab": [
        "[lemma1]",
        "[lemma2]"
      ]
    }
  ],
  "questions": [
    {
      "id": "de-b1-l-t1-{SLUG}-q1",
      "module": "lesen",
      "teil": 1,
      "type": "richtig_falsch",
      "question": "[Frage / question]",
      "correct": "Richtig",
      "correctAnswer": "Richtig",
      "explanation": "[kurze Begründung / short justification]",
      "passageId": "de-b1-p-lesen-t1-{SLUG}",
      "options": [],
      "grammarTags": [
        "g-de-b1-[tag]"
      ],
      "topicTags": [
        "[topic]"
      ],
      "vocabularyTags": [
        "[lemma]"
      ],
      "difficulty": 5,
      "skills": [
        "reading"
      ],
      "language": "de",
      "level": "B1",
      "examType": "goethe"
    },
    {
      "id": "de-b1-l-t1-{SLUG}-q2",
      "module": "lesen",
      "teil": 1,
      "type": "richtig_falsch",
      "question": "[Frage / question]",
      "correct": "Richtig",
      "correctAnswer": "Richtig",
      "explanation": "[kurze Begründung / short justification]",
      "passageId": "de-b1-p-lesen-t1-{SLUG}",
      "options": [],
      "grammarTags": [
        "g-de-b1-[tag]"
      ],
      "topicTags": [
        "[topic]"
      ],
      "vocabularyTags": [
        "[lemma]"
      ],
      "difficulty": 5,
      "skills": [
        "reading"
      ],
      "language": "de",
      "level": "B1",
      "examType": "goethe"
    },
    {
      "id": "de-b1-l-t1-{SLUG}-q3",
      "module": "lesen",
      "teil": 1,
      "type": "richtig_falsch",
      "question": "[Frage / question]",
      "correct": "Richtig",
      "correctAnswer": "Richtig",
      "explanation": "[kurze Begründung / short justification]",
      "passageId": "de-b1-p-lesen-t1-{SLUG}",
      "options": [],
      "grammarTags": [
        "g-de-b1-[tag]"
      ],
      "topicTags": [
        "[topic]"
      ],
      "vocabularyTags": [
        "[lemma]"
      ],
      "difficulty": 5,
      "skills": [
        "reading"
      ],
      "language": "de",
      "level": "B1",
      "examType": "goethe"
    },
    {
      "id": "de-b1-l-t1-{SLUG}-q4",
      "module": "lesen",
      "teil": 1,
      "type": "richtig_falsch",
      "question": "[Frage / question]",
      "correct": "Richtig",
      "correctAnswer": "Richtig",
      "explanation": "[kurze Begründung / short justification]",
      "passageId": "de-b1-p-lesen-t1-{SLUG}",
      "options": [],
      "grammarTags": [
        "g-de-b1-[tag]"
      ],
      "topicTags": [
        "[topic]"
      ],
      "vocabularyTags": [
        "[lemma]"
      ],
      "difficulty": 5,
      "skills": [
        "reading"
      ],
      "language": "de",
      "level": "B1",
      "examType": "goethe"
    },
    {
      "id": "de-b1-l-t1-{SLUG}-q5",
      "module": "lesen",
      "teil": 1,
      "type": "richtig_falsch",
      "question": "[Frage / question]",
      "correct": "Richtig",
      "correctAnswer": "Richtig",
      "explanation": "[kurze Begründung / short justification]",
      "passageId": "de-b1-p-lesen-t1-{SLUG}",
      "options": [],
      "grammarTags": [
        "g-de-b1-[tag]"
      ],
      "topicTags": [
        "[topic]"
      ],
      "vocabularyTags": [
        "[lemma]"
      ],
      "difficulty": 5,
      "skills": [
        "reading"
      ],
      "language": "de",
      "level": "B1",
      "examType": "goethe"
    },
    {
      "id": "de-b1-l-t1-{SLUG}-q6",
      "module": "lesen",
      "teil": 1,
      "type": "richtig_falsch",
      "question": "[Frage / question]",
      "correct": "Richtig",
      "correctAnswer": "Richtig",
      "explanation": "[kurze Begründung / short justification]",
      "passageId": "de-b1-p-lesen-t1-{SLUG}",
      "options": [],
      "grammarTags": [
        "g-de-b1-[tag]"
      ],
      "topicTags": [
        "[topic]"
      ],
      "vocabularyTags": [
        "[lemma]"
      ],
      "difficulty": 5,
      "skills": [
        "reading"
      ],
      "language": "de",
      "level": "B1",
      "examType": "goethe"
    }
  ]
}
